app/__init__.py
app/query_printer.py
app/query_tracker.py
sqa_tracker-0.1.2.dist-info/LICENSE
sqa_tracker-0.1.2.dist-info/METADATA
sqa_tracker-0.1.2.dist-info/WHEEL
sqa_tracker-0.1.2.dist-info/RECORD
