Metadata-Version: 2.3
Name: sqa-tracker
Version: 0.1.2
Summary: A tool to track SQLAlchemy query modifications with a structured execution tree and diffs.
License: MIT
Author: Jiri Otoupal
Author-email: jiri-otoupal@ips-database.eu
Requires-Python: >=3.10
Classifier: License :: OSI Approved :: MIT License
Classifier: Programming Language :: Python :: 3
Classifier: Programming Language :: Python :: 3.10
Classifier: Programming Language :: Python :: 3.11
Classifier: Programming Language :: Python :: 3.12
Classifier: Programming Language :: Python :: 3.13
Requires-Dist: rich (>=13.9.4,<14.0.0)
